mcp_benchmark/__init__.py
mcp_benchmark/clients/__init__.py
mcp_benchmark/servers/__init__.py
mcp_benchmark/servers/weather.py
mcp_benchmark/tasks/__init__.py
mcp_benchmark/tasks/example.py
mcp_benchmark-0.0.1.dev0.dist-info/METADATA
mcp_benchmark-0.0.1.dev0.dist-info/WHEEL
mcp_benchmark-0.0.1.dev0.dist-info/top_level.txt
mcp_benchmark-0.0.1.dev0.dist-info/RECORD
